<?xml version="1.0" encoding="UTF-8"?>
<odoo>
  <record model="ir.ui.view" id="careone_access.careone_salesperson_access">
		<field name="name">careone_access.careone_salesperson_access</field>
		<field name="model">mrp.production</field>
		<field name="inherit_id" ref="mrp.mrp_production_form_view"/>
    <field name="groups_id" eval="[(4, ref('careone_access.careone_salesperson'))]"/>
		<field name="arch" type="xml">
      <!-- <xpath expr="//form/header" position="inside">
        <field name="current_group_mrp" invisible="1"/>
      </xpath> -->
      <xpath expr="//form" position="attributes">
          <attribute name="edit">false</attribute>
     </xpath>
		</field>
	</record>
  <record model="ir.ui.view" id="careone_access.careone_salesperson_accesses">
		<field name="name">careone_access.careone_salesperson_accesses</field>
		<field name="model">sale.order</field>
		<field name="inherit_id" ref="sale.view_order_form"/>
    <field name="groups_id" eval="[(4, ref('careone_access.careone_salesperson'))]"/>
		<field name="arch" type="xml">
			<xpath expr="//form/header/button[@name='action_cancel']" position="attributes">
        <attribute name="invisible">1</attribute>
			</xpath>
      <xpath expr="//form/header/button[@name='action_draft']" position="attributes">
        <attribute name="invisible">1</attribute>
			</xpath>
		</field>
	</record>
</odoo>
